{
    "base_font": "nunito-sans",
    "palette": "blue",
    "favicon": "images/logotipo/cbs_icon.ico",
    "header": {
        "logo_img": "images/logotipo/cbs-logo-full.svg",
        "logo_img_alt": "Logo Clube Brasil Seguros -",
        "has_nav": true,
        "nav_links": [
            {
                "label": "Sobre",
                "url": "/#sobre",
                "style": "link"
            },
            {
                "label": "Coberturas e Assistências",
                "url": "/#coberturas",
                "style": "link"
            },
            {
                "label": "Parceiros",
                "url": "/#parceiros",
                "style": "link"
            },
            {
                "label": "Clientes",
                "url": "/#clientes",
                "style": "link"
            },
            {
                "label": "Contato",
                "url": "/#contato",
                "style": "link"
            },
            {
                "label": "Simule aqui",
                "url": "http://www.clubebrasilseguros.com/",
                "style": "primary"
            }
        ]
    },
    "footer": {
        "sections": [
            {
                "type": "footer_text",
                "image": "images/logotipo/CBS-white.svg",
                "image_url": "/",
                "image_alt": "Footer logo",
                "content": "Clube Brasil Seguros"
            },
            {
                "type": "footer_text",
                "title": "Fale Conosco",
                "content": 
                "Avenida das Américas, 2480 - Bloco 2 / 308 - Barra da Tijuca, Rio de Janeiro (RJ)\n\nTelefone: (21) 3952-0100\n\nSAC: 0800 391 9388\n\nAssistência 24 horas: 0800 721 3875\n\nE-mail: atendimento@clubebrasilseguros.com"
            }
        ],
        "has_nav": true,
        "content": "&copy; Clube Brasil Seguros. Todos os direitos reservados. As imagens contidas neste site são de uso gratuito."
    },
    "title": "Clube Brasil Seguros"
}